MMSICHE/MMSICHE.py
MMSICHE/__init__.py
MMSICHE-1.0.4.dist-info/LICENSE.txt
MMSICHE-1.0.4.dist-info/METADATA
MMSICHE-1.0.4.dist-info/WHEEL
MMSICHE-1.0.4.dist-info/top_level.txt
MMSICHE-1.0.4.dist-info/RECORD
